<?xml version="1.0" encoding="utf-8"?>
<_2014.10.05_10-32-42_PM_text_results><query>dig</query><ip>::1</ip><host_name>Unknown host</host_name><query_time>2014-10-05 10:32:41 PM</query_time><consumed>0.141</consumed><total_results>304</total_results><num_of_results>10</num_of_results><from>1</from><to>10</to><text_results><text_result><num>1</num><weight>100.0</weight><url>../../modules/hesperian_health/en_cgeh_2012_full/page327.html</url><title> How to double &amp;#60;span class&amp;#61;&amp;#34;mak_1&amp;#34;&amp;#62;&amp;#60;span class&amp;#61;&amp;#34;mak_1&amp;#34;&amp;#62;dig &amp;#60;/span&amp;#62;&amp;#60;/span&amp;#62;a garden bed - A Community Guide to Environmental Health - Page ...</title><fulltxt>&amp;#60;ul&amp;#62;&amp;#13;&amp;#10;                        &amp;#60;li&amp;#62;&amp;#60;strong&amp;#62;.&amp;#160;.&amp;#160;.&amp;#160;&amp;#60;/strong&amp;#62; Health Printable PDF  Sustainable Farming in the Cit y 311 How to double dig a garden bed To grow as much as possible in a small area or to plant on hard soils or soils with little organic matter double digging is a good method &amp;#226;&amp;#158;&amp;#138; The ed&amp;#60;strong&amp;#62;&amp;#160;&amp;#160;.&amp;#160;.&amp;#160;.&amp;#60;/strong&amp;#62;&amp;#60;/li&amp;#62;&amp;#13;&amp;#10;                        &amp;#60;li&amp;#62;&amp;#60;strong&amp;#62;.&amp;#160;.&amp;#160;.&amp;#160;&amp;#60;/strong&amp;#62; spread finished compost or manure on top of the whole bed &amp;#226;&amp;#158;&amp;#140; Starting at one end dig a ditch across the bed 30 cm deep and 30 cm wide topsoil manure &amp;#226;&amp;#158;&amp;#141; Use a digging fork or shovel to loosen the soil at the bottom of the ditch and add some compo&amp;#60;strong&amp;#62;.&amp;#160;.&amp;#160;.&amp;#160;&amp;#60;/strong&amp;#62;&amp;#60;/li&amp;#62;&amp;#13;&amp;#10;                    &amp;#60;li&amp;#62;&amp;#60;strong&amp;#62;.&amp;#160;.&amp;#160;.&amp;#160;&amp;#60;/strong&amp;#62; loosen the soil at the bottom of the ditch and add some compost or manure to it &amp;#226;&amp;#158;&amp;#142; Dig a second ditch across the bed Put the soil from the second ditch into the first ditch Loosen the soil at the bottom and spread compost or manure &amp;#226;&amp;#158;&amp;#143; Continue unt&amp;#60;strong&amp;#62;.&amp;#160;.&amp;#160;.&amp;#160;&amp;#60;/strong&amp;#62;&amp;#60;/li&amp;#62;&amp;#13;&amp;#10;                    &amp;#60;/ul&amp;#62;</fulltxt><page_size>31.4 kb</page_size><domain_name></domain_name></text_result><text_result><num>2</num><weight>73.6</weight><url>../../modules/wikipedia_for_schools/images/2564/256430.jpg.htm</url><title> Children are &amp;#60;span class&amp;#61;&amp;#34;mak_1&amp;#34;&amp;#62;&amp;#60;span class&amp;#61;&amp;#34;mak_1&amp;#34;&amp;#62;digg&amp;#60;/span&amp;#62;&amp;#60;/span&amp;#62;ing up frozen potatoes in the field of a collective farm. Udachne ...</title><fulltxt>&amp;#60;span class&amp;#61;&amp;#39;warn&amp;#39;&amp;#62;The exact search string was not found in the text, however it did contain related words.&amp;#60;/span&amp;#62;</fulltxt><page_size>12.2 kb</page_size><domain_name></domain_name></text_result><text_result><num>3</num><weight>73.6</weight><url>../../modules/wikipedia_for_schools/images/1045/104596.jpg.htm</url><title> Canterbury Big &amp;#60;span class&amp;#61;&amp;#34;mak_1&amp;#34;&amp;#62;&amp;#60;span class&amp;#61;&amp;#34;mak_1&amp;#34;&amp;#62;Dig &amp;#60;/span&amp;#62;&amp;#60;/span&amp;#62;2.JPG  - Image</title><fulltxt>&amp;#60;ul&amp;#62;&amp;#60;li&amp;#62;  Canterbury Big Dig 2 JPG an image on an on the for from  canterbury big dig 2 jpg picture image Canterbury Big Dig 2 JPG &amp;#60;/li&amp;#62;</fulltxt><page_size>14.5 kb</page_size><domain_name></domain_name></text_result><text_result><num>4</num><weight>69.8</weight><url>../../modules/wikipedia_for_schools/images/1201/120110.jpg.htm</url><title> Volleyball &amp;#60;span class&amp;#61;&amp;#34;mak_1&amp;#34;&amp;#62;&amp;#60;span class&amp;#61;&amp;#34;mak_1&amp;#34;&amp;#62;dig.&amp;#60;/span&amp;#62;&amp;#60;/span&amp;#62;jpg  - Image</title><fulltxt>&amp;#60;ul&amp;#62;&amp;#60;li&amp;#62;  Volleyball dig jpg an image on an on the for from  volleyball defense picture image Volleyball dig jpg &amp;#60;/li&amp;#62;</fulltxt><page_size>15.4 kb</page_size><domain_name></domain_name></text_result><text_result><num>5</num><weight>32.1</weight><url>../../modules/wikipedia_for_schools/wp/v/Volleyball.htm</url><title> Volleyball </title><fulltxt>&amp;#60;ul&amp;#62;&amp;#13;&amp;#10;                        &amp;#60;li&amp;#62;&amp;#60;strong&amp;#62;.&amp;#160;.&amp;#160;.&amp;#160;&amp;#60;/strong&amp;#62; players arranged in the rest of the court attempt to control the ball with a dig  usually a fore-arm pass of a hard-driven ball  After a successful dig the team transitions to offense The game continues in this manner rallying back and forth&amp;#60;strong&amp;#62;&amp;#160;&amp;#160;.&amp;#160;.&amp;#160;.&amp;#60;/strong&amp;#62;&amp;#60;/li&amp;#62;&amp;#13;&amp;#10;                        &amp;#60;li&amp;#62;&amp;#60;strong&amp;#62;.&amp;#160;.&amp;#160;.&amp;#160;&amp;#60;/strong&amp;#62; Skills Competitive teams master six basic skills serve pass set attack block and dig Each of these skills comprises a number of specific techniques that have been introduced over the years and are now considered standard practice in high-level&amp;#60;strong&amp;#62;.&amp;#160;.&amp;#160;.&amp;#160;&amp;#60;/strong&amp;#62;&amp;#60;/li&amp;#62;&amp;#13;&amp;#10;                    &amp;#60;li&amp;#62;&amp;#60;strong&amp;#62;.&amp;#160;.&amp;#160;.&amp;#160;&amp;#60;/strong&amp;#62; positions where other defenders place themselves while opponent hitters are spiking Dig Woman going for a dig Digging is the ability to prevent the ball from touching on s court after a spike or attack particularly a ball that is nearly touching&amp;#60;strong&amp;#62;.&amp;#160;.&amp;#160;.&amp;#160;&amp;#60;/strong&amp;#62;&amp;#60;/li&amp;#62;&amp;#13;&amp;#10;                    &amp;#60;/ul&amp;#62;</fulltxt><page_size>62.9 kb</page_size><domain_name></domain_name></text_result><text_result><num>6</num><weight>28.3</weight><url>../../modules/wikipedia_for_schools/wp/t/Trench_warfare.htm</url><title> Trench warfare </title><fulltxt>&amp;#60;ul&amp;#62;&amp;#13;&amp;#10;                        &amp;#60;li&amp;#62;&amp;#60;strong&amp;#62;.&amp;#160;.&amp;#160;.&amp;#160;&amp;#60;/strong&amp;#62; without exposing themselves over the parapet There were three standard ways to dig a trench entrenching sapping and tunneling Entrenching where a man would stand on the surface and dig downwards was most efficient as it allowed a large digging&amp;#60;strong&amp;#62;&amp;#160;&amp;#160;.&amp;#160;.&amp;#160;.&amp;#60;/strong&amp;#62;&amp;#60;/li&amp;#62;&amp;#13;&amp;#10;                        &amp;#60;li&amp;#62;&amp;#60;strong&amp;#62;.&amp;#160;.&amp;#160;.&amp;#160;&amp;#60;/strong&amp;#62; surface and dig downwards was most efficient as it allowed a large digging party to dig the full length of the trench simultaneously However entrenching left the diggers exposed above ground and hence could only be carried out when free of&amp;#60;strong&amp;#62;.&amp;#160;.&amp;#160;.&amp;#160;&amp;#60;/strong&amp;#62;&amp;#60;/li&amp;#62;&amp;#13;&amp;#10;                    &amp;#60;li&amp;#62;&amp;#60;strong&amp;#62;.&amp;#160;.&amp;#160;.&amp;#160;&amp;#60;/strong&amp;#62; to use in the confined quarters of the trenches These tools could then be used to dig in after they had taken a trench Since the troops were often not adequately equipped for trench warfare improvised weapons were common in the first encounters&amp;#60;strong&amp;#62;.&amp;#160;.&amp;#160;.&amp;#160;&amp;#60;/strong&amp;#62;&amp;#60;/li&amp;#62;&amp;#13;&amp;#10;                    &amp;#60;/ul&amp;#62;</fulltxt><page_size>107.0 kb</page_size><domain_name></domain_name></text_result><text_result><num>7</num><weight>22.6</weight><url>../../modules/wikipedia_for_schools/wp/e/European_badger.htm</url><title> European badger </title><fulltxt>&amp;#60;ul&amp;#62;&amp;#13;&amp;#10;                        &amp;#60;li&amp;#62;&amp;#60;strong&amp;#62;.&amp;#160;.&amp;#160;.&amp;#160;&amp;#60;/strong&amp;#62; is on average 74&amp;#160;cm &amp;#215;&amp;#160;76&amp;#160;cm  29&amp;#160;in &amp;#215;&amp;#160;30&amp;#160;in  and are 38&amp;#160;cm  15&amp;#160;in  high Badgers dig and collect bedding throughout the year particularly in autumn and spring Sett maintenance is usually carried out by subordinate sows and dominant boars The sett&amp;#60;strong&amp;#62;&amp;#160;&amp;#160;.&amp;#160;.&amp;#160;.&amp;#60;/strong&amp;#62;&amp;#60;/li&amp;#62;&amp;#13;&amp;#10;                        &amp;#60;li&amp;#62;&amp;#60;strong&amp;#62;.&amp;#160;.&amp;#160;.&amp;#160;&amp;#60;/strong&amp;#62; a badger dies within a sett chamber its conspecifics will seal off the chamber and dig a new one Some badgers will drag their dead out of the sett and bury them outside A sett is almost invariably located near a tree which is used by badgers for&amp;#60;strong&amp;#62;.&amp;#160;.&amp;#160;.&amp;#160;&amp;#60;/strong&amp;#62;&amp;#60;/li&amp;#62;&amp;#13;&amp;#10;                    &amp;#60;li&amp;#62;&amp;#60;strong&amp;#62;.&amp;#160;.&amp;#160;.&amp;#160;&amp;#60;/strong&amp;#62; They catch young rabbits by locating their position in their nest by scent then dig vertically downwards to it In mountainous or hilly districts where vegetable food is scarce badgers rely on rabbits as a principal food source Adult rabbits are&amp;#60;strong&amp;#62;.&amp;#160;.&amp;#160;.&amp;#160;&amp;#60;/strong&amp;#62;&amp;#60;/li&amp;#62;&amp;#13;&amp;#10;                    &amp;#60;/ul&amp;#62;</fulltxt><page_size>50.1 kb</page_size><domain_name></domain_name></text_result><text_result><num>8</num><weight>22.6</weight><url>../../modules/wikipedia_for_schools/wp/p/Phoenix_%2528spacecraft%2529.htm</url><title> Phoenix (spacecraft) </title><fulltxt>&amp;#60;ul&amp;#62;&amp;#13;&amp;#10;                        &amp;#60;li&amp;#62;&amp;#60;strong&amp;#62;.&amp;#160;.&amp;#160;.&amp;#160;&amp;#60;/strong&amp;#62;  is designed to extend 2 35&amp;#160;m from its base on the lander and have the ability to dig down to 0 5&amp;#160;m below the surface It will take samples of dirt and ice that will be analyzed by other instruments on the lander The arm was designed and built for &amp;#60;strong&amp;#62;&amp;#160;&amp;#160;.&amp;#160;.&amp;#160;.&amp;#60;/strong&amp;#62;&amp;#60;/li&amp;#62;&amp;#13;&amp;#10;                        &amp;#60;/ul&amp;#62;</fulltxt><page_size>71.6 kb</page_size><domain_name></domain_name></text_result><text_result><num>9</num><weight>22.6</weight><url>../../modules/wikipedia_for_schools/wp/f/Frog.htm</url><title> Frog </title><fulltxt>&amp;#60;ul&amp;#62;&amp;#13;&amp;#10;                        &amp;#60;li&amp;#62;&amp;#60;strong&amp;#62;.&amp;#160;.&amp;#160;.&amp;#160;&amp;#60;/strong&amp;#62; in winter Those that live on land such as the American toad Bufo americanus dig a burrow and make a hibernaculum in which to lie dormant Others less proficient at digging find a crevice or bury themselves in dead leaves Aquatic species such&amp;#60;strong&amp;#62;&amp;#160;&amp;#160;.&amp;#160;.&amp;#160;.&amp;#60;/strong&amp;#62;&amp;#60;/li&amp;#62;&amp;#13;&amp;#10;                        &amp;#60;li&amp;#62;&amp;#60;strong&amp;#62;.&amp;#160;.&amp;#160;.&amp;#160;&amp;#60;/strong&amp;#62; bone attached to one of the metatarsals of the hind foot which it uses to dig itself backwards into the ground As it digs the toad wriggles its hips from side to side in order to sink into the loose soil It has a shallow burrow in the&amp;#60;strong&amp;#62;.&amp;#160;.&amp;#160;.&amp;#160;&amp;#60;/strong&amp;#62;&amp;#60;/li&amp;#62;&amp;#13;&amp;#10;                    &amp;#60;/ul&amp;#62;</fulltxt><page_size>218.2 kb</page_size><domain_name></domain_name></text_result><text_result><num>10</num><weight>18.9</weight><url>../../modules/wikipedia_for_schools/wp/a/Aardvark.htm</url><title> Aardvark </title><fulltxt>&amp;#60;ul&amp;#62;&amp;#13;&amp;#10;                        &amp;#60;li&amp;#62;&amp;#60;strong&amp;#62;.&amp;#160;.&amp;#160;.&amp;#160;&amp;#60;/strong&amp;#62; exceptionally fast digger but otherwise moves fairly slowly Its claws enable it to dig through the extremely hard crust of a termite or ant mound quickly avoiding the dust by sealing the nostrils When successful the aardvar s long  as long as 30&amp;#60;strong&amp;#62;&amp;#160;&amp;#160;.&amp;#160;.&amp;#160;.&amp;#60;/strong&amp;#62;&amp;#60;/li&amp;#62;&amp;#13;&amp;#10;                        &amp;#60;li&amp;#62;&amp;#60;strong&amp;#62;.&amp;#160;.&amp;#160;.&amp;#160;&amp;#60;/strong&amp;#62; termites at 14 weeks and is weaned by 16 weeks At six months of age it is able to dig its own burrows but it will often remain with the mother until the next mating season and is sexually capable by the season after that Aardvarks can live to be&amp;#60;strong&amp;#62;.&amp;#160;.&amp;#160;.&amp;#160;&amp;#60;/strong&amp;#62;&amp;#60;/li&amp;#62;&amp;#13;&amp;#10;                    &amp;#60;li&amp;#62;&amp;#60;strong&amp;#62;.&amp;#160;.&amp;#160;.&amp;#160;&amp;#60;/strong&amp;#62; aardvar s main predators are lions leopards hunting dogs and pythons Aardvarks can dig fast or run in zigzag fashion to elude enemies but if all else fails they will strike with their claws tail and shoulders sometimes flipping onto their backs to&amp;#60;strong&amp;#62;.&amp;#160;.&amp;#160;.&amp;#160;&amp;#60;/strong&amp;#62;&amp;#60;/li&amp;#62;&amp;#13;&amp;#10;                    &amp;#60;/ul&amp;#62;</fulltxt><page_size>17.6 kb</page_size><domain_name></domain_name></text_result></text_results><pages>31</pages><prev>0</prev><next>2</next><start>1</start></_2014.10.05_10-32-42_PM_text_results>
