<?xml version="1.0" encoding="utf-8"?>
<_2014.06.16_11-30-37_PM_text_results><query>markup</query><ip>::1</ip><host_name>Unknown host</host_name><query_time>2014-06-16 11:30:36 PM</query_time><consumed>0.014</consumed><total_results>2</total_results><num_of_results>2</num_of_results><from>1</from><to>2</to><text_results><text_result><num>1</num><weight>100.0</weight><url>http://localhost/RACHEL/rachel/content/mods/wikipedia-schools-en/wp/m/Markup_language.htm</url><title> &amp;#60;span class&amp;#61;&amp;#34;mak_1&amp;#34;&amp;#62;&amp;#60;span class&amp;#61;&amp;#34;mak_1&amp;#34;&amp;#62;Markup &amp;#60;/span&amp;#62;&amp;#60;/span&amp;#62;language </title><fulltxt>&amp;#60;ul&amp;#62;&amp;#13;&amp;#10;                        &amp;#60;li&amp;#62;   Markup language Related subjects Computer Programming Background Information Arranging a Wikipedia selection for schools in the developing world without internet was an initiative by SOS Children All children available for child sponsorship from&amp;#60;strong&amp;#62;&amp;#160;&amp;#160;.&amp;#160;.&amp;#160;.&amp;#60;/strong&amp;#62;&amp;#60;/li&amp;#62;&amp;#13;&amp;#10;                            &amp;#60;li&amp;#62;&amp;#60;strong&amp;#62;.&amp;#160;.&amp;#160;.&amp;#160;&amp;#60;/strong&amp;#62; after in a family home by the charity Read more  Example of RecipeBook a simple markup language based on XML for creating recipes The markup can be converted to HTML PDF and Rich Text Format using a programming language or XSL A markup language&amp;#60;strong&amp;#62;.&amp;#160;.&amp;#160;.&amp;#160;&amp;#60;/strong&amp;#62;&amp;#60;/li&amp;#62;&amp;#13;&amp;#10;                    &amp;#60;li&amp;#62;&amp;#60;strong&amp;#62;.&amp;#160;.&amp;#160;.&amp;#160;&amp;#60;/strong&amp;#62; to text that describe how text is to be structured laid out or formatted Markup languages have been in use for centuries and in recent years have also been used in computer typesetting and word-processing systems A well-known example of&amp;#60;strong&amp;#62;.&amp;#160;.&amp;#160;.&amp;#160;&amp;#60;/strong&amp;#62;&amp;#60;/li&amp;#62;&amp;#13;&amp;#10;                    &amp;#60;/ul&amp;#62;</fulltxt><page_size>19.6 kb</page_size><domain_name>localhost/publizieren/http:/</domain_name></text_result><text_result><num>2</num><weight>7.1</weight><url>http://localhost/RACHEL/rachel/content/mods/wikipedia-schools-en/wp/w/World_Wide_Web.htm</url><title> World Wide Web </title><fulltxt>&amp;#60;ul&amp;#62;&amp;#13;&amp;#10;                        &amp;#60;li&amp;#62;&amp;#60;strong&amp;#62;.&amp;#160;.&amp;#160;.&amp;#160;&amp;#60;/strong&amp;#62;  URL  and uniform resource identifier  URI the publishing language HyperText Markup Language  HTML the Hypertext Transfer Protocol  HTTP  The World Wide Web had a number of differences from other hypertext systems that were then available&amp;#60;strong&amp;#62;&amp;#160;&amp;#160;.&amp;#160;.&amp;#160;.&amp;#60;/strong&amp;#62;&amp;#60;/li&amp;#62;&amp;#13;&amp;#10;                        &amp;#60;li&amp;#62;&amp;#60;strong&amp;#62;.&amp;#160;.&amp;#160;.&amp;#160;&amp;#60;/strong&amp;#62; has played an active role in guiding the development of web standards  such as the markup languages in which web pages are composed  and in recent years has advocated his vision of a Semantic Web The World Wide Web enabled the spread of&amp;#60;strong&amp;#62;.&amp;#160;.&amp;#160;.&amp;#160;&amp;#60;/strong&amp;#62;&amp;#60;/li&amp;#62;&amp;#13;&amp;#10;                    &amp;#60;li&amp;#62;&amp;#60;strong&amp;#62;.&amp;#160;.&amp;#160;.&amp;#160;&amp;#60;/strong&amp;#62; html  charset UTF-8 followed by the content of the requested page The Hypertext Markup Language for a basic web page looks like The World Wide Web abbreviated as WWW and commonly known The web browser parses the HTML interpreting the markup for&amp;#60;strong&amp;#62;.&amp;#160;.&amp;#160;.&amp;#160;&amp;#60;/strong&amp;#62;&amp;#60;/li&amp;#62;&amp;#13;&amp;#10;                    &amp;#60;/ul&amp;#62;</fulltxt><page_size>52.2 kb</page_size><domain_name>localhost/publizieren/http:/</domain_name></text_result></text_results></_2014.06.16_11-30-37_PM_text_results>
