<?xml version="1.0" encoding="utf-8"?>
<text_results><query>test</query><ip>192.168.1.50</ip><host_name>WP-NUC</host_name><query_time>2014-10-20 01:50:34 AM</query_time><consumed>4.167</consumed><total_results>999</total_results><num_of_results>10</num_of_results><from>1</from><to>10</to><text_results><text_result><num>1</num><weight>100.0</weight><url>../../modules/hesperian_health/en_cgeh_2012_full/page86.html</url><title> &amp;#60;span class&amp;#61;&amp;#34;mak_1&amp;#34;&amp;#62;&amp;#60;span class&amp;#61;&amp;#34;mak_1&amp;#34;&amp;#62;Testi&amp;#60;/span&amp;#62;&amp;#60;/span&amp;#62;ng for water safety - A Community Guide to Environmental Health - Page 86 </title><fulltxt>&amp;#60;ul&amp;#62;&amp;#13;&amp;#10;                        &amp;#60;li&amp;#62;&amp;#60;strong&amp;#62;.&amp;#160;.&amp;#160;.&amp;#160;&amp;#60;/strong&amp;#62; awareness of water issues and careful protection of water sources  see page 75  H2S test Some water testing kits can be used locally to test water for germs For example the &amp;#226;&amp;#128;&amp;#156;H2S test&amp;#226;&amp;#128;&amp;#157; is low cost  5 tests cost about 1 dollar  and gives quick res&amp;#60;strong&amp;#62;&amp;#160;&amp;#160;.&amp;#160;.&amp;#160;.&amp;#60;/strong&amp;#62;&amp;#60;/li&amp;#62;&amp;#13;&amp;#10;                        &amp;#60;li&amp;#62;&amp;#60;strong&amp;#62;.&amp;#160;.&amp;#160;.&amp;#160;&amp;#60;/strong&amp;#62; test&amp;#226;&amp;#128;&amp;#157; is low cost  5 tests cost about 1 dollar  and gives quick results But this test sometimes mistakes harmless living things for germs and it does not show if chemicals or parasite eggs are in the water Water quality tests show only if the wa&amp;#60;strong&amp;#62;.&amp;#160;.&amp;#160;.&amp;#160;&amp;#60;/strong&amp;#62;&amp;#60;/li&amp;#62;&amp;#13;&amp;#10;                    &amp;#60;/ul&amp;#62;</fulltxt><page_size>33.6 kb</page_size><domain_name>localhost/publizieren/http:/</domain_name></text_result><text_result><num>2</num><weight>100.0</weight><url>../../modules/hesperian_health/ehb_water_EN_watermark/page11.html</url><title> &amp;#60;span class&amp;#61;&amp;#34;mak_1&amp;#34;&amp;#62;&amp;#60;span class&amp;#61;&amp;#34;mak_1&amp;#34;&amp;#62;Testi&amp;#60;/span&amp;#62;&amp;#60;/span&amp;#62;ng for water safety - Water for Life - Community water security - Page 11 </title><fulltxt>&amp;#60;ul&amp;#62;&amp;#13;&amp;#10;                        &amp;#60;li&amp;#62;&amp;#60;strong&amp;#62;.&amp;#160;.&amp;#160;.&amp;#160;&amp;#60;/strong&amp;#62; 11 Testing for water safety Testing water in a laboratory or with a water quality test kit can show the type and amount of contamination Water testing may be done by professionals who take samples of local water to a laboratory to test it&amp;#60;strong&amp;#62;&amp;#160;&amp;#160;.&amp;#160;.&amp;#160;.&amp;#60;/strong&amp;#62;&amp;#60;/li&amp;#62;&amp;#13;&amp;#10;                        &amp;#60;li&amp;#62;&amp;#60;strong&amp;#62;.&amp;#160;.&amp;#160;.&amp;#160;&amp;#60;/strong&amp;#62; may be done by professionals who take samples of local water to a laboratory to test it Laboratory testing is usually necessary to find chemical contamination These tests are helpful but can be costly Testing water for germs may be done locally&amp;#60;strong&amp;#62;.&amp;#160;.&amp;#160;.&amp;#160;&amp;#60;/strong&amp;#62;&amp;#60;/li&amp;#62;&amp;#13;&amp;#10;                    &amp;#60;li&amp;#62;&amp;#60;strong&amp;#62;.&amp;#160;.&amp;#160;.&amp;#160;&amp;#60;/strong&amp;#62; are helpful but can be costly Testing water for germs may be done locally using a test kit One kind of test kit called the H2S test is widely used to test for germs in water It is not costly  5 tests cost about 1 dollar  and it gives quick&amp;#60;strong&amp;#62;.&amp;#160;.&amp;#160;.&amp;#160;&amp;#60;/strong&amp;#62;&amp;#60;/li&amp;#62;&amp;#13;&amp;#10;                    &amp;#60;/ul&amp;#62;</fulltxt><page_size>12.2 kb</page_size><domain_name>localhost/publizieren/http:/</domain_name></text_result><text_result><num>3</num><weight>100.0</weight><url>../../modules/hesperian_health/en_hhwl_2012_full/page182.html</url><title> The Function of &amp;#60;span class&amp;#61;&amp;#34;mak_1&amp;#34;&amp;#62;&amp;#60;span class&amp;#61;&amp;#34;mak_1&amp;#34;&amp;#62;Tests&amp;#60;/span&amp;#62;&amp;#60;/span&amp;#62; and Exams in - Helping Health Workers Learn - Page 182 </title><fulltxt>&amp;#60;ul&amp;#62;&amp;#13;&amp;#10;                        &amp;#60;li&amp;#62;&amp;#60;strong&amp;#62;.&amp;#160;.&amp;#160;.&amp;#160;&amp;#60;/strong&amp;#62; and ideas already covered in class Nothing new So tests are usually boring &amp;#226;&amp;#128;&amp;#162;&amp;#9; All test questions have a right or wrong answer not open to question by the students &amp;#226;&amp;#128;&amp;#162;&amp;#9; Teacher usually corrects the tests &amp;#226;&amp;#128;&amp;#162;&amp;#9; Atmosphere of trust Teacher may leave r&amp;#60;strong&amp;#62;&amp;#160;&amp;#160;.&amp;#160;.&amp;#160;.&amp;#60;/strong&amp;#62;&amp;#60;/li&amp;#62;&amp;#13;&amp;#10;                        &amp;#60;li&amp;#62;&amp;#60;strong&amp;#62;.&amp;#160;.&amp;#160;.&amp;#160;&amp;#60;/strong&amp;#62; emphasis on understanding Notes or books may be used during most exams Since exams test how well students can apply their learning in real- life situations the use of books and other available resources is encouraged &amp;#226;&amp;#128;&amp;#162;&amp;#9; Test questions are de&amp;#60;strong&amp;#62;.&amp;#160;.&amp;#160;.&amp;#160;&amp;#60;/strong&amp;#62;&amp;#60;/li&amp;#62;&amp;#13;&amp;#10;                    &amp;#60;li&amp;#62;&amp;#60;strong&amp;#62;.&amp;#160;.&amp;#160;.&amp;#160;&amp;#60;/strong&amp;#62; &amp;#226;&amp;#128;&amp;#148;not simply repeat &amp;#226;&amp;#128;&amp;#162;&amp;#9; No strict time limit Extra time is allowed after the test so slower readers can finish Or they can take tests none to complete &amp;#226;&amp;#128;&amp;#162;&amp;#9; Tests try to introduce new ideas and understanding building on material covered in cla&amp;#60;strong&amp;#62;.&amp;#160;.&amp;#160;.&amp;#160;&amp;#60;/strong&amp;#62;&amp;#60;/li&amp;#62;&amp;#13;&amp;#10;                    &amp;#60;/ul&amp;#62;</fulltxt><page_size>46.2 kb</page_size><domain_name>localhost/publizieren/http:/</domain_name></text_result><text_result><num>4</num><weight>96.6</weight><url>../../modules/hesperian_health/en_hhwl_2012_full/page477.html</url><title> &amp;#60;span class&amp;#61;&amp;#34;mak_1&amp;#34;&amp;#62;&amp;#60;span class&amp;#61;&amp;#34;mak_1&amp;#34;&amp;#62;Testi&amp;#60;/span&amp;#62;&amp;#60;/span&amp;#62;ng children&amp;#8217;s eyesight - Helping Health Workers Learn - Page 477 </title><fulltxt>&amp;#60;ul&amp;#62;&amp;#13;&amp;#10;                        &amp;#60;li&amp;#62;&amp;#60;strong&amp;#62;.&amp;#160;.&amp;#160;.&amp;#160;&amp;#60;/strong&amp;#62; on white cardboard 24- 13 After the children practice testing each other they can test the eyesight of those in the younger grades and the children who will be starting school soon Also make a large &amp;#226;&amp;#128;&amp;#152;E&amp;#226;&amp;#128;&amp;#153; shape out of cardboard or other mater&amp;#60;strong&amp;#62;&amp;#160;&amp;#160;.&amp;#160;.&amp;#160;.&amp;#60;/strong&amp;#62;&amp;#60;/li&amp;#62;&amp;#13;&amp;#10;                        &amp;#60;li&amp;#62;&amp;#60;strong&amp;#62;.&amp;#160;.&amp;#160;.&amp;#160;&amp;#60;/strong&amp;#62; a large &amp;#226;&amp;#128;&amp;#152;E&amp;#226;&amp;#128;&amp;#153; shape out of cardboard or other material First let the children test each other Hang the chart in a place where the light is good Then make a line about 6 meters from the chart The child to be tested stands behind the line holdi&amp;#60;strong&amp;#62;.&amp;#160;.&amp;#160;.&amp;#160;&amp;#60;/strong&amp;#62;&amp;#60;/li&amp;#62;&amp;#13;&amp;#10;                    &amp;#60;li&amp;#62;&amp;#60;strong&amp;#62;.&amp;#160;.&amp;#160;.&amp;#160;&amp;#60;/strong&amp;#62; the cut-out &amp;#226;&amp;#128;&amp;#152;E&amp;#226;&amp;#128;&amp;#153; in the same direction as the letter pointed to on the chart Test each eye by covering the other If the child can easily see the &amp;#226;&amp;#128;&amp;#152;E&amp;#226;&amp;#128;&amp;#153;s on the bottom line he sees welt If he has trouble seeing the second or third line he see&amp;#60;strong&amp;#62;.&amp;#160;.&amp;#160;.&amp;#160;&amp;#60;/strong&amp;#62;&amp;#60;/li&amp;#62;&amp;#13;&amp;#10;                    &amp;#60;/ul&amp;#62;</fulltxt><page_size>38.3 kb</page_size><domain_name>localhost/publizieren/http:/</domain_name></text_result><text_result><num>5</num><weight>96.6</weight><url>../../modules/hesperian_health/DVC_2009/page48.html</url><title> Muscle &amp;#60;span class&amp;#61;&amp;#34;mak_1&amp;#34;&amp;#62;&amp;#60;span class&amp;#61;&amp;#34;mak_1&amp;#34;&amp;#62;testi&amp;#60;/span&amp;#62;&amp;#60;/span&amp;#62;ng - Disabled Village Children - Page 48 </title><fulltxt>&amp;#60;ul&amp;#62;&amp;#13;&amp;#10;                        &amp;#60;li&amp;#62;&amp;#60;strong&amp;#62;.&amp;#160;.&amp;#160;.&amp;#160;&amp;#60;/strong&amp;#62; 30 chapter 4 Muscle testing Muscle strength can be anywhere between normal and zero Test it like this If the child can lift the weight of leg all the way press down on it to check if she can hold up as much weight as is normal for a girl her age If&amp;#60;strong&amp;#62;&amp;#160;&amp;#160;.&amp;#160;.&amp;#160;.&amp;#60;/strong&amp;#62;&amp;#60;/li&amp;#62;&amp;#13;&amp;#10;                        &amp;#60;li&amp;#62;&amp;#60;strong&amp;#62;.&amp;#160;.&amp;#160;.&amp;#160;&amp;#60;/strong&amp;#62; her TRACE Muscles move but not leg TRACE strength No muscle movement ZERO strength Test the strength of all muscles that might be affected Here are some of the muscle tests that are most useful for figuring out the difficulties and needs of&amp;#60;strong&amp;#62;.&amp;#160;.&amp;#160;.&amp;#160;&amp;#60;/strong&amp;#62;&amp;#60;/li&amp;#62;&amp;#13;&amp;#10;                    &amp;#60;li&amp;#62;&amp;#60;strong&amp;#62;.&amp;#160;.&amp;#160;.&amp;#160;&amp;#60;/strong&amp;#62; difficulties and needs of different children Note These tests are simple and mostly test the strength of groups of muscles Physical therapists know ways to test for strength of individual muscles Ankle and Foot DOWN UP BEND IN BEND OUT If the child&amp;#60;strong&amp;#62;.&amp;#160;.&amp;#160;.&amp;#160;&amp;#60;/strong&amp;#62;&amp;#60;/li&amp;#62;&amp;#13;&amp;#10;                    &amp;#60;/ul&amp;#62;</fulltxt><page_size>45.4 kb</page_size><domain_name>localhost/publizieren/http:/</domain_name></text_result><text_result><num>6</num><weight>93.2</weight><url>../../modules/hesperian_health/en_hhwl_2012_full/page353.html</url><title> Specific &amp;#60;span class&amp;#61;&amp;#34;mak_1&amp;#34;&amp;#62;&amp;#60;span class&amp;#61;&amp;#34;mak_1&amp;#34;&amp;#62;tests&amp;#60;/span&amp;#62;&amp;#60;/span&amp;#62; and examinations, and more questions ... - Helping Health Workers ...</title><fulltxt>&amp;#60;ul&amp;#62;&amp;#13;&amp;#10;                        &amp;#60;li&amp;#62;&amp;#60;strong&amp;#62;.&amp;#160;.&amp;#160;.&amp;#160;&amp;#60;/strong&amp;#62; laboratory or hospital that can do what is needed Be sure to discuss this rebound test as shown in WTND 9 &amp;#9; Diagnosis Decide  if you can which cause of the problem is most likely It is important that the diagnosis not be considered a certainty&amp;#60;strong&amp;#62;&amp;#160;&amp;#160;.&amp;#160;.&amp;#160;.&amp;#60;/strong&amp;#62;&amp;#60;/li&amp;#62;&amp;#13;&amp;#10;                        &amp;#60;li&amp;#62;&amp;#60;strong&amp;#62;.&amp;#160;.&amp;#160;.&amp;#160;&amp;#60;/strong&amp;#62; more real the person pretending to be sick should supply a clinical history and test results typical for one of the possible causes of the woman&amp;#226;&amp;#128;&amp;#153;s pain&amp;#226;&amp;#128;&amp;#148;gallbladder disease for example Then the students can actually follow the step-by-step me&amp;#60;strong&amp;#62;.&amp;#160;.&amp;#160;.&amp;#160;&amp;#60;/strong&amp;#62;&amp;#60;/li&amp;#62;&amp;#13;&amp;#10;                    &amp;#60;/ul&amp;#62;</fulltxt><page_size>37.0 kb</page_size><domain_name>localhost/publizieren/http:/</domain_name></text_result><text_result><num>7</num><weight>89.8</weight><url>../../modules/hesperian_health/DVC_2009/page47.html</url><title> Precautions when &amp;#60;span class&amp;#61;&amp;#34;mak_1&amp;#34;&amp;#62;&amp;#60;span class&amp;#61;&amp;#34;mak_1&amp;#34;&amp;#62;testi&amp;#60;/span&amp;#62;&amp;#60;/span&amp;#62;ng for contractures - Disabled Village Children - Page 47 ...</title><fulltxt>&amp;#60;ul&amp;#62;&amp;#13;&amp;#10;                        &amp;#60;li&amp;#62;&amp;#60;strong&amp;#62;.&amp;#160;.&amp;#160;.&amp;#160;&amp;#60;/strong&amp;#62; when testing for contractures of ankles and hips 29 Ankle normal upward bend Test the range of motion with the knee as straight as it will go With the knee bent the foot will usually bend up more But for walking we need to know how far it&amp;#60;strong&amp;#62;&amp;#160;&amp;#160;.&amp;#160;.&amp;#160;.&amp;#60;/strong&amp;#62;&amp;#60;/li&amp;#62;&amp;#13;&amp;#10;                        &amp;#60;li&amp;#62;&amp;#60;strong&amp;#62;.&amp;#160;.&amp;#160;.&amp;#160;&amp;#60;/strong&amp;#62; contracture  See p 79  Feel the tight cord here If the knee will not straighten test him with his leg over the edge of a table CAUTION The hips will often straighten more at an angle to the body So be sure to lower the leg in a straight line&amp;#60;strong&amp;#62;.&amp;#160;.&amp;#160;.&amp;#160;&amp;#60;/strong&amp;#62;&amp;#60;/li&amp;#62;&amp;#13;&amp;#10;                    &amp;#60;/ul&amp;#62;</fulltxt><page_size>36.4 kb</page_size><domain_name>localhost/publizieren/http:/</domain_name></text_result><text_result><num>8</num><weight>89.8</weight><url>../../modules/hesperian_health/DVC_2009/page471.html</url><title> &amp;#60;span class&amp;#61;&amp;#34;mak_1&amp;#34;&amp;#62;&amp;#60;span class&amp;#61;&amp;#34;mak_1&amp;#34;&amp;#62;Testi&amp;#60;/span&amp;#62;&amp;#60;/span&amp;#62;ng how well children see (4 years old and older) - Disabled Village Children ...</title><fulltxt>&amp;#60;ul&amp;#62;&amp;#13;&amp;#10;                        &amp;#60;li&amp;#62;&amp;#60;strong&amp;#62;.&amp;#160;.&amp;#160;.&amp;#160;&amp;#60;/strong&amp;#62; one large &amp;#226;&amp;#128;&amp;#152;E&amp;#226;&amp;#128;&amp;#153; shape out of cardboard or other material First let the children test each other Hang the chart in a place where the light is good Then make a line about 6 meters from the chart The child to be tested stands behind the line holdi&amp;#60;strong&amp;#62;&amp;#160;&amp;#160;.&amp;#160;.&amp;#160;.&amp;#60;/strong&amp;#62;&amp;#60;/li&amp;#62;&amp;#13;&amp;#10;                        &amp;#60;li&amp;#62;&amp;#60;strong&amp;#62;.&amp;#160;.&amp;#160;.&amp;#160;&amp;#60;/strong&amp;#62; on the chart or to tell you for each &amp;#226;&amp;#128;&amp;#152;C&amp;#226;&amp;#128;&amp;#153; which way the horse shoe is going To test children who are mentally slow deaf or have trouble communicating you can use pictures of different things they recognize Hold up one picture at a time and have&amp;#60;strong&amp;#62;.&amp;#160;.&amp;#160;.&amp;#160;&amp;#60;/strong&amp;#62;&amp;#60;/li&amp;#62;&amp;#13;&amp;#10;                    &amp;#60;/ul&amp;#62;</fulltxt><page_size>37.5 kb</page_size><domain_name>localhost/publizieren/http:/</domain_name></text_result><text_result><num>9</num><weight>89.8</weight><url>../../modules/hesperian_health/DVC_2009/page45.html</url><title> &amp;#60;span class&amp;#61;&amp;#34;mak_1&amp;#34;&amp;#62;&amp;#60;span class&amp;#61;&amp;#34;mak_1&amp;#34;&amp;#62;TESTI&amp;#60;/span&amp;#62;&amp;#60;/span&amp;#62;NG RANGE OF MOTION OF JOINTS - Disabled Village Children - Page 45 </title><fulltxt>&amp;#60;ul&amp;#62;&amp;#13;&amp;#10;                        &amp;#60;li&amp;#62;&amp;#60;strong&amp;#62;.&amp;#160;.&amp;#160;.&amp;#160;&amp;#60;/strong&amp;#62; of muscles or joint pain or scarring from injuries or burns it is a good idea to test and record both RANGE OF MOTION and MUSCLE STRENGTH of all parts of the body that might have contractures or be affected There are 2 reasons for this &amp;#226;&amp;#128;&amp;#162;&amp;#9; Kn&amp;#60;strong&amp;#62;&amp;#160;&amp;#160;.&amp;#160;.&amp;#160;.&amp;#60;/strong&amp;#62;&amp;#60;/li&amp;#62;&amp;#13;&amp;#10;                        &amp;#60;li&amp;#62;&amp;#60;strong&amp;#62;.&amp;#160;.&amp;#160;.&amp;#160;&amp;#60;/strong&amp;#62; active persons They should be of the same ages as the disabled children you will test Age matters because babies are usually weaker and have much more flexible joints than older children For example A baby&amp;#226;&amp;#128;&amp;#153;s back and hips bend so much he can li&amp;#60;strong&amp;#62;.&amp;#160;.&amp;#160;.&amp;#160;&amp;#60;/strong&amp;#62;&amp;#60;/li&amp;#62;&amp;#13;&amp;#10;                    &amp;#60;/ul&amp;#62;</fulltxt><page_size>42.8 kb</page_size><domain_name>localhost/publizieren/http:/</domain_name></text_result><text_result><num>10</num><weight>89.8</weight><url>../../modules/hesperian_health/en_wwhnd_2012_full/page301.html</url><title> The disadvantages of knowing the &amp;#60;span class&amp;#61;&amp;#34;mak_1&amp;#34;&amp;#62;&amp;#60;span class&amp;#61;&amp;#34;mak_1&amp;#34;&amp;#62;test &amp;#60;/span&amp;#62;&amp;#60;/span&amp;#62;results - Where Women Have No Doctor - Page ...</title><fulltxt>&amp;#60;ul&amp;#62;&amp;#13;&amp;#10;                        &amp;#60;li&amp;#62;   Where Women Have No Doctor Printable PDF  The disadvantages of knowing the test results You may have many different feelings if you find out you are infected with HIV It is normal at first to be shocked and deny that your test results are&amp;#60;strong&amp;#62;&amp;#160;&amp;#160;.&amp;#160;.&amp;#160;.&amp;#60;/strong&amp;#62;&amp;#60;/li&amp;#62;&amp;#13;&amp;#10;                            &amp;#60;li&amp;#62;&amp;#60;strong&amp;#62;.&amp;#160;.&amp;#160;.&amp;#160;&amp;#60;/strong&amp;#62; It often helps to talk with someone such as the health worker who gave you the test results or someone close to you But be careful who you tell Your husband or partner may blame you even if he is also infected with HIV Other people may act&amp;#60;strong&amp;#62;.&amp;#160;.&amp;#160;.&amp;#160;&amp;#60;/strong&amp;#62;&amp;#60;/li&amp;#62;&amp;#13;&amp;#10;                    &amp;#60;li&amp;#62;&amp;#60;strong&amp;#62;.&amp;#160;.&amp;#160;.&amp;#160;&amp;#60;/strong&amp;#62; can help you decide who to tell and how to face this change in your life The HIV Test 289 IMPORTANT A negative test only means that you do not have HIV when the test is taken If you do not protect yourself you can still get infected Practice&amp;#60;strong&amp;#62;.&amp;#160;.&amp;#160;.&amp;#160;&amp;#60;/strong&amp;#62;&amp;#60;/li&amp;#62;&amp;#13;&amp;#10;                    &amp;#60;/ul&amp;#62;</fulltxt><page_size>34.6 kb</page_size><domain_name>localhost/publizieren/http:/</domain_name></text_result></text_results><pages>100</pages><prev>0</prev><next>2</next><start>1</start></text_results>
